vegas_ai/__init__.py
vegas_ai/vegas.py
vegas_ai-1.0.1.dist-info/LICENSE
vegas_ai-1.0.1.dist-info/METADATA
vegas_ai-1.0.1.dist-info/WHEEL
vegas_ai-1.0.1.dist-info/top_level.txt
vegas_ai-1.0.1.dist-info/RECORD
