Metadata-Version: 2.2
Name: vegas_ai
Version: 1.0.1
Summary: A simple library for randomly selecting winners and to test if this class works.
Home-page: https://github.com/newarsaurav/vegas_ai.git
Author: Saurav Shrestha , Winsmano awazico ambani
Author-email: newarsaurav@gmail.com
Classifier: Programming Language :: Python :: 3
Classifier: License :: OSI Approved :: MIT License
Classifier: Operating System :: OS Independent
Requires-Python: >=3.6
License-File: LICENSE
Dynamic: author
Dynamic: author-email
Dynamic: classifier
Dynamic: description
Dynamic: description-content-type
Dynamic: home-page
Dynamic: requires-python
Dynamic: summary
